adios4dolfinx/__init__.py
adios4dolfinx/adios2_helpers.py
adios4dolfinx/checkpointing.py
adios4dolfinx/comm_helpers.py
adios4dolfinx/legacy_readers.py
adios4dolfinx/original_checkpoint.py
adios4dolfinx/py.typed
adios4dolfinx/snapshot.py
adios4dolfinx/structures.py
adios4dolfinx/utils.py
adios4dolfinx/writers.py
adios4dolfinx-0.10.0.post0.dist-info/licenses/LICENSE
adios4dolfinx-0.10.0.post0.dist-info/METADATA
adios4dolfinx-0.10.0.post0.dist-info/WHEEL
adios4dolfinx-0.10.0.post0.dist-info/top_level.txt
adios4dolfinx-0.10.0.post0.dist-info/RECORD
