Metadata-Version: 2.4
Name: adios4dolfinx
Version: 0.10.0.post0
Summary: Checkpointing functionality for DOLFINx meshes/functions with ADIOS2
Author-email: "Jørgen S. Dokken" <dokken@simula.no>
License: Copyright 2023 Jørgen S. Dokken
License-File: LICENSE
Requires-Dist: fenics-dolfinx>=0.9.0
Requires-Dist: packaging
Provides-Extra: test
Requires-Dist: pytest; extra == "test"
Requires-Dist: coverage; extra == "test"
Requires-Dist: ipyparallel; extra == "test"
Provides-Extra: dev
Requires-Dist: pdbpp; extra == "dev"
Requires-Dist: ipython; extra == "dev"
Requires-Dist: mypy; extra == "dev"
Requires-Dist: ruff; extra == "dev"
Provides-Extra: docs
Requires-Dist: jupyter-book; extra == "docs"
Requires-Dist: ipyparallel; extra == "docs"
Requires-Dist: ipywidgets; extra == "docs"
Requires-Dist: jupytext; extra == "docs"
Requires-Dist: ipykernel<7.0.0; extra == "docs"
Requires-Dist: sphinx-codeautolink; extra == "docs"
Provides-Extra: all
Requires-Dist: adios4dolfinx[dev,docs,test]; extra == "all"
Dynamic: license-file
